puffling/__about__.py
puffling/__init__.py
puffling/__main__.py
puffling/build.py
puffling/build_self.py
puffling/py.typed
puffling/bridge/__init__.py
puffling/bridge/app.py
puffling/builders/__init__.py
puffling/builders/app.py
puffling/builders/config.py
puffling/builders/constants.py
puffling/builders/custom.py
puffling/builders/sdist.py
puffling/builders/utils.py
puffling/builders/wheel.py
puffling/builders/hooks/__init__.py
puffling/builders/hooks/custom.py
puffling/builders/hooks/version.py
puffling/builders/hooks/plugin/__init__.py
puffling/builders/hooks/plugin/hooks.py
puffling/builders/hooks/plugin/interface.py
puffling/builders/plugin/__init__.py
puffling/builders/plugin/hooks.py
puffling/builders/plugin/interface.py
puffling/cli/__init__.py
puffling/cli/build/__init__.py
puffling/cli/dep/__init__.py
puffling/cli/metadata/__init__.py
puffling/cli/version/__init__.py
puffling/dep/__init__.py
puffling/dep/core.py
puffling/licenses/__init__.py
puffling/licenses/parse.py
puffling/licenses/supported.py
puffling/metadata/__init__.py
puffling/metadata/core.py
puffling/metadata/custom.py
puffling/metadata/spec.py
puffling/metadata/utils.py
puffling/metadata/plugin/__init__.py
puffling/metadata/plugin/hooks.py
puffling/metadata/plugin/interface.py
puffling/plugin/__init__.py
puffling/plugin/exceptions.py
puffling/plugin/manager.py
puffling/plugin/specs.py
puffling/plugin/utils.py
puffling/utils/__init__.py
puffling/utils/constants.py
puffling/utils/context.py
puffling/utils/fs.py
puffling/version/__init__.py
puffling/version/core.py
puffling/version/scheme/__init__.py
puffling/version/scheme/standard.py
puffling/version/scheme/plugin/__init__.py
puffling/version/scheme/plugin/hooks.py
puffling/version/scheme/plugin/interface.py
puffling/version/source/__init__.py
puffling/version/source/code.py
puffling/version/source/env.py
puffling/version/source/regex.py
puffling/version/source/plugin/__init__.py
puffling/version/source/plugin/hooks.py
puffling-0.1.1.dist-info/METADATA
puffling-0.1.1.dist-info/WHEEL
puffling-0.1.1.dist-info/entry_points.txt
puffling-0.1.1.dist-info/licenses/LICENSE-APACHE
puffling-0.1.1.dist-info/licenses/LICENSE-MIT
puffling-0.1.1.dist-info/RECORD
